<?xml version="1.0" encoding="utf-8"?>
<clothing-items>
 <clothing>
  <id>
   670880191
  </id>
  <name>
   Adidas Belts S-7233
  </name>
  <category>
   Belts
  </category>
  <size>
   XL
  </size>
  <color>
   Синий
  </color>
  <material>
   Полиэстер
  </material>
  <price>
   170639
  </price>
  <rating>
   2.31
  </rating>
  <reviews>
   992560
  </reviews>
  <new>
   -
  </new>
  <sporty>
   no
  </sporty>
 </clothing>
 <clothing>
  <id>
   867141539
  </id>
  <name>
   Under Armour Belts L-4056
  </name>
  <category>
   Belts
  </category>
  <size>
   XXL
  </size>
  <color>
   Красный
  </color>
  <material>
   Хлопок
  </material>
  <price>
   856147
  </price>
  <rating>
   2.18
  </rating>
  <reviews>
   247443
  </reviews>
  <new>
   +
  </new>
  <sporty>
   yes
  </sporty>
 </clothing>
 <clothing>
  <id>
   742787935
  </id>
  <name>
   Fila Dress L-8777
  </name>
  <category>
   Dress
  </category>
  <size>
   L
  </size>
  <color>
   Голубой
  </color>
  <material>
   Шерсть
  </material>
  <price>
   177832
  </price>
  <rating>
   2.33
  </rating>
  <reviews>
   554819
  </reviews>
 </clothing>
 <clothing>
  <id>
   587841011
  </id>
  <name>
   Vans Shirt W-5838
  </name>
  <category>
   Shirt
  </category>
  <size>
   XXL
  </size>
  <color>
   Синий
  </color>
  <material>
   Вискоза
  </material>
  <price>
   923693
  </price>
  <rating>
   4.28
  </rating>
  <reviews>
   82704
  </reviews>
  <new>
   +
  </new>
  <exclusive>
   yes
  </exclusive>
  <sporty>
   no
  </sporty>
 </clothing>
 <clothing>
  <id>
   544793358
  </id>
  <name>
   Reebok Shoes M-5821
  </name>
  <category>
   Shoes
  </category>
  <size>
   XXL
  </size>
  <color>
   Красный
  </color>
  <material>
   Нейлон
  </material>
  <price>
   445874
  </price>
  <rating>
   3.77
  </rating>
  <reviews>
   989505
  </reviews>
  <new>
   +
  </new>
  <sporty>
   yes
  </sporty>
 </clothing>
 <clothing>
  <id>
   689903156
  </id>
  <name>
   Under Armour Shoes D-5584
  </name>
  <category>
   Shoes
  </category>
  <size>
   XL
  </size>
  <color>
   Синий
  </color>
  <material>
   Нейлон
  </material>
  <price>
   842138
  </price>
  <rating>
   4.53
  </rating>
  <reviews>
   161126
  </reviews>
  <new>
   -
  </new>
  <exclusive>
   no
  </exclusive>
  <sporty>
   yes
  </sporty>
 </clothing>
 <clothing>
  <id>
   716088129
  </id>
  <name>
   Ellesse Sweater C-3890
  </name>
  <category>
   Sweater
  </category>
  <size>
   XL
  </size>
  <color>
   Фиолетовый
  </color>
  <material>
   Шерсть
  </material>
  <price>
   780826
  </price>
  <rating>
   3.38
  </rating>
  <reviews>
   357301
  </reviews>
  <exclusive>
   no
  </exclusive>
 </clothing>
 <clothing>
  <id>
   536477306
  </id>
  <name>
   Brooks Belts Q-8521
  </name>
  <category>
   Belts
  </category>
  <size>
   S
  </size>
  <color>
   Голубой
  </color>
  <material>
   Шелк
  </material>
  <price>
   551388
  </price>
  <rating>
   4.6
  </rating>
  <reviews>
   954817
  </reviews>
  <new>
   -
  </new>
  <exclusive>
   no
  </exclusive>
  <sporty>
   no
  </sporty>
 </clothing>
 <clothing>
  <id>
   733466611
  </id>
  <name>
   Adidas Jacket P-7796
  </name>
  <category>
   Jacket
  </category>
  <size>
   L
  </size>
  <color>
   Голубой
  </color>
  <material>
   Шелк
  </material>
  <price>
   741624
  </price>
  <rating>
   1.45
  </rating>
  <reviews>
   634215
  </reviews>
  <new>
   +
  </new>
  <sporty>
   no
  </sporty>
 </clothing>
 <clothing>
  <id>
   922991583
  </id>
  <name>
   Vans Skirt G-2864
  </name>
  <category>
   Skirt
  </category>
  <size>
   L
  </size>
  <color>
   Зеленый
  </color>
  <material>
   Лен
  </material>
  <price>
   392619
  </price>
  <rating>
   3.46
  </rating>
  <reviews>
   483346
  </reviews>
  <new>
   -
  </new>
  <exclusive>
   no
  </exclusive>
 </clothing>
 <clothing>
  <id>
   124330940
  </id>
  <name>
   DC Shirt A-6195
  </name>
  <category>
   Shirt
  </category>
  <size>
   L
  </size>
  <color>
   Голубой
  </color>
  <material>
   Вискоза
  </material>
  <price>
   147251
  </price>
  <rating>
   1.57
  </rating>
  <reviews>
   212406
  </reviews>
  <sporty>
   yes
  </sporty>
 </clothing>
 <clothing>
  <id>
   240484953
  </id>
  <name>
   Reebok Belts G-6773
  </name>
  <category>
   Belts
  </category>
  <size>
   S
  </size>
  <color>
   Оранжевый
  </color>
  <material>
   Хлопок
  </material>
  <price>
   707443
  </price>
  <rating>
   3.81
  </rating>
  <reviews>
   899721
  </reviews>
  <sporty>
   no
  </sporty>
 </clothing>
 <clothing>
  <id>
   451348851
  </id>
  <name>
   Addidas Socks R-4242
  </name>
  <category>
   Socks
  </category>
  <size>
   XL
  </size>
  <color>
   Голубой
  </color>
  <material>
   Полиэстер
  </material>
  <price>
   778523
  </price>
  <rating>
   4.69
  </rating>
  <reviews>
   174874
  </reviews>
  <new>
   -
  </new>
  <sporty>
   no
  </sporty>
 </clothing>
 <clothing>
  <id>
   381513115
  </id>
  <name>
   Fila Gloves O-8137
  </name>
  <category>
   Gloves
  </category>
  <size>
   XXL
  </size>
  <color>
   Голубой
  </color>
  <material>
   Кожа
  </material>
  <price>
   970400
  </price>
  <rating>
   1.43
  </rating>
  <reviews>
   748313
  </reviews>
  <exclusive>
   no
  </exclusive>
 </clothing>
 <clothing>
  <id>
   282946281
  </id>
  <name>
   Converse Sweater V-1806
  </name>
  <category>
   Sweater
  </category>
  <size>
   L
  </size>
  <color>
   Фиолетовый
  </color>
  <material>
   Хлопок
  </material>
  <price>
   620525
  </price>
  <rating>
   2.64
  </rating>
  <reviews>
   128227
  </reviews>
  <new>
   +
  </new>
  <sporty>
   yes
  </sporty>
 </clothing>
 <clothing>
  <id>
   788550500
  </id>
  <name>
   Converse Umbrellas F-5603
  </name>
  <category>
   Umbrellas
  </category>
  <size>
   XL
  </size>
  <color>
   Оранжевый
  </color>
  <material>
   Кожа
  </material>
  <price>
   127734
  </price>
  <rating>
   3.38
  </rating>
  <reviews>
   873865
  </reviews>
  <sporty>
   no
  </sporty>
 </clothing>
 <clothing>
  <id>
   334838939
  </id>
  <name>
   DC Dress W-9489
  </name>
  <category>
   Dress
  </category>
  <size>
   M
  </size>
  <color>
   Красный
  </color>
  <material>
   Вискоза
  </material>
  <price>
   396907
  </price>
  <rating>
   3.09
  </rating>
  <reviews>
   46242
  </reviews>
  <sporty>
   yes
  </sporty>
 </clothing>
 <clothing>
  <id>
   174660836
  </id>
  <name>
   Puma Hat N-5000
  </name>
  <category>
   Hat
  </category>
  <size>
   S
  </size>
  <color>
   Фиолетовый
  </color>
  <material>
   Кожа
  </material>
  <price>
   524944
  </price>
  <rating>
   3.83
  </rating>
  <reviews>
   391091
  </reviews>
  <exclusive>
   yes
  </exclusive>
 </clothing>
 <clothing>
  <id>
   860188603
  </id>
  <name>
   Puma Gloves P-2510
  </name>
  <category>
   Gloves
  </category>
  <size>
   S
  </size>
  <color>
   Зеленый
  </color>
  <material>
   Лен
  </material>
  <price>
   444257
  </price>
  <rating>
   3.9
  </rating>
  <reviews>
   92201
  </reviews>
  <new>
   -
  </new>
  <sporty>
   yes
  </sporty>
 </clothing>
 <clothing>
  <id>
   952704621
  </id>
  <name>
   Fila Blouse N-1183
  </name>
  <category>
   Blouse
  </category>
  <size>
   XL
  </size>
  <color>
   Оранжевый
  </color>
  <material>
   Полиэстер
  </material>
  <price>
   628740
  </price>
  <rating>
   3.69
  </rating>
  <reviews>
   940855
  </reviews>
  <exclusive>
   yes
  </exclusive>
  <sporty>
   yes
  </sporty>
 </clothing>
 <clothing>
  <id>
   398589556
  </id>
  <name>
   Converse Blouse S-5371
  </name>
  <category>
   Blouse
  </category>
  <size>
   XL
  </size>
  <color>
   Оранжевый
  </color>
  <material>
   Шерсть
  </material>
  <price>
   348561
  </price>
  <rating>
   3.56
  </rating>
  <reviews>
   555129
  </reviews>
  <exclusive>
   yes
  </exclusive>
  <sporty>
   no
  </sporty>
 </clothing>
 <clothing>
  <id>
   719997179
  </id>
  <name>
   Fila Hat P-3313
  </name>
  <category>
   Hat
  </category>
  <size>
   XL
  </size>
  <color>
   Синий
  </color>
  <material>
   Полиэстер
  </material>
  <price>
   679102
  </price>
  <rating>
   3.65
  </rating>
  <reviews>
   747711
  </reviews>
 </clothing>
 <clothing>
  <id>
   788705479
  </id>
  <name>
   New Balance Shoes B-6853
  </name>
  <category>
   Shoes
  </category>
  <size>
   XL
  </size>
  <color>
   Красный
  </color>
  <material>
   Лен
  </material>
  <price>
   390254
  </price>
  <rating>
   2.6
  </rating>
  <reviews>
   860226
  </reviews>
  <exclusive>
   no
  </exclusive>
  <sporty>
   yes
  </sporty>
 </clothing>
 <clothing>
  <id>
   976826341
  </id>
  <name>
   Asics Pants A-3460
  </name>
  <category>
   Pants
  </category>
  <size>
   S
  </size>
  <color>
   Синий
  </color>
  <material>
   Нейлон
  </material>
  <price>
   926349
  </price>
  <rating>
   3.09
  </rating>
  <reviews>
   77467
  </reviews>
  <exclusive>
   no
  </exclusive>
 </clothing>
 <clothing>
  <id>
   443718343
  </id>
  <name>
   Puma Skirt W-6673
  </name>
  <category>
   Skirt
  </category>
  <size>
   M
  </size>
  <color>
   Фиолетовый
  </color>
  <material>
   Полиэстер
  </material>
  <price>
   444212
  </price>
  <rating>
   1.53
  </rating>
  <reviews>
   363630
  </reviews>
  <new>
   +
  </new>
  <sporty>
   yes
  </sporty>
 </clothing>
 <clothing>
  <id>
   715257532
  </id>
  <name>
   Converse Blouse D-2978
  </name>
  <category>
   Blouse
  </category>
  <size>
   M
  </size>
  <color>
   Голубой
  </color>
  <material>
   Кожа
  </material>
  <price>
   248850
  </price>
  <rating>
   4.69
  </rating>
  <reviews>
   325295
  </reviews>
  <exclusive>
   no
  </exclusive>
  <sporty>
   no
  </sporty>
 </clothing>
 <clothing>
  <id>
   916333570
  </id>
  <name>
   Asics Gloves T-6180
  </name>
  <category>
   Gloves
  </category>
  <size>
   M
  </size>
  <color>
   Фиолетовый
  </color>
  <material>
   Нейлон
  </material>
  <price>
   629615
  </price>
  <rating>
   1.41
  </rating>
  <reviews>
   219169
  </reviews>
 </clothing>
 <clothing>
  <id>
   827506684
  </id>
  <name>
   Under Armour Belts L-6309
  </name>
  <category>
   Belts
  </category>
  <size>
   M
  </size>
  <color>
   Красный
  </color>
  <material>
   Вискоза
  </material>
  <price>
   760952
  </price>
  <rating>
   1.65
  </rating>
  <reviews>
   686843
  </reviews>
  <exclusive>
   no
  </exclusive>
  <sporty>
   no
  </sporty>
 </clothing>
 <clothing>
  <id>
   527379561
  </id>
  <name>
   Puma Sweater L-9027
  </name>
  <category>
   Sweater
  </category>
  <size>
   L
  </size>
  <color>
   Желтый
  </color>
  <material>
   Вискоза
  </material>
  <price>
   998751
  </price>
  <rating>
   3.37
  </rating>
  <reviews>
   488140
  </reviews>
  <new>
   -
  </new>
  <exclusive>
   yes
  </exclusive>
  <sporty>
   no
  </sporty>
 </clothing>
 <clothing>
  <id>
   452528407
  </id>
  <name>
   Nike Jeans P-5673
  </name>
  <category>
   Jeans
  </category>
  <size>
   L
  </size>
  <color>
   Синий
  </color>
  <material>
   Полиэстер
  </material>
  <price>
   725313
  </price>
  <rating>
   4.07
  </rating>
  <reviews>
   272902
  </reviews>
  <sporty>
   yes
  </sporty>
 </clothing>
 <clothing>
  <id>
   916671786
  </id>
  <name>
   Vans Blouse Q-8821
  </name>
  <category>
   Blouse
  </category>
  <size>
   M
  </size>
  <color>
   Голубой
  </color>
  <material>
   Вискоза
  </material>
  <price>
   385634
  </price>
  <rating>
   4.43
  </rating>
  <reviews>
   744749
  </reviews>
  <new>
   -
  </new>
  <sporty>
   no
  </sporty>
 </clothing>
 <clothing>
  <id>
   901319991
  </id>
  <name>
   Addidas Skirt M-6181
  </name>
  <category>
   Skirt
  </category>
  <size>
   M
  </size>
  <color>
   Зеленый
  </color>
  <material>
   Шелк
  </material>
  <price>
   377586
  </price>
  <rating>
   2.55
  </rating>
  <reviews>
   156670
  </reviews>
  <exclusive>
   yes
  </exclusive>
 </clothing>
 <clothing>
  <id>
   415895129
  </id>
  <name>
   Asics Socks A-2052
  </name>
  <category>
   Socks
  </category>
  <size>
   L
  </size>
  <color>
   Красный
  </color>
  <material>
   Кожа
  </material>
  <price>
   882223
  </price>
  <rating>
   3.79
  </rating>
  <reviews>
   443499
  </reviews>
  <exclusive>
   no
  </exclusive>
 </clothing>
 <clothing>
  <id>
   750085385
  </id>
  <name>
   Reebok T-shirt Y-3293
  </name>
  <category>
   T-shirt
  </category>
  <size>
   L
  </size>
  <color>
   Оранжевый
  </color>
  <material>
   Шелк
  </material>
  <price>
   870652
  </price>
  <rating>
   3.25
  </rating>
  <reviews>
   519645
  </reviews>
  <exclusive>
   no
  </exclusive>
  <sporty>
   no
  </sporty>
 </clothing>
 <clothing>
  <id>
   342932783
  </id>
  <name>
   DC Dress T-9525
  </name>
  <category>
   Dress
  </category>
  <size>
   XL
  </size>
  <color>
   Голубой
  </color>
  <material>
   Кожа
  </material>
  <price>
   672463
  </price>
  <rating>
   3.18
  </rating>
  <reviews>
   803688
  </reviews>
  <new>
   +
  </new>
  <exclusive>
   yes
  </exclusive>
 </clothing>
 <clothing>
  <id>
   898389513
  </id>
  <name>
   Reebok Blouse F-6501
  </name>
  <category>
   Blouse
  </category>
  <size>
   XXL
  </size>
  <color>
   Синий
  </color>
  <material>
   Лен
  </material>
  <price>
   249661
  </price>
  <rating>
   4.47
  </rating>
  <reviews>
   426095
  </reviews>
  <new>
   +
  </new>
  <sporty>
   yes
  </sporty>
 </clothing>
 <clothing>
  <id>
   220404940
  </id>
  <name>
   Addidas Belts G-4240
  </name>
  <category>
   Belts
  </category>
  <size>
   XL
  </size>
  <color>
   Оранжевый
  </color>
  <material>
   Хлопок
  </material>
  <price>
   977495
  </price>
  <rating>
   3.65
  </rating>
  <reviews>
   297570
  </reviews>
  <exclusive>
   no
  </exclusive>
  <sporty>
   yes
  </sporty>
 </clothing>
 <clothing>
  <id>
   359158369
  </id>
  <name>
   Fila Pants B-5007
  </name>
  <category>
   Pants
  </category>
  <size>
   M
  </size>
  <color>
   Зеленый
  </color>
  <material>
   Нейлон
  </material>
  <price>
   776716
  </price>
  <rating>
   2.79
  </rating>
  <reviews>
   361878
  </reviews>
  <new>
   +
  </new>
  <exclusive>
   no
  </exclusive>
  <sporty>
   no
  </sporty>
 </clothing>
 <clothing>
  <id>
   790706079
  </id>
  <name>
   Converse Jacket S-6193
  </name>
  <category>
   Jacket
  </category>
  <size>
   M
  </size>
  <color>
   Оранжевый
  </color>
  <material>
   Шерсть
  </material>
  <price>
   670632
  </price>
  <rating>
   2.4
  </rating>
  <reviews>
   237089
  </reviews>
  <new>
   +
  </new>
  <exclusive>
   no
  </exclusive>
  <sporty>
   no
  </sporty>
 </clothing>
 <clothing>
  <id>
   636798830
  </id>
  <name>
   Asics Shirt X-5378
  </name>
  <category>
   Shirt
  </category>
  <size>
   S
  </size>
  <color>
   Синий
  </color>
  <material>
   Кожа
  </material>
  <price>
   598655
  </price>
  <rating>
   3.02
  </rating>
  <reviews>
   251931
  </reviews>
  <new>
   -
  </new>
  <exclusive>
   no
  </exclusive>
  <sporty>
   yes
  </sporty>
 </clothing>
</clothing-items>
