<?xml version="1.0" encoding="utf-8"?>
<clothing-items>
 <clothing>
  <id>
   657997871
  </id>
  <name>
   Ellesse Blouse M-4099
  </name>
  <category>
   Blouse
  </category>
  <size>
   S
  </size>
  <color>
   Красный
  </color>
  <material>
   Хлопок
  </material>
  <price>
   641874
  </price>
  <rating>
   4.67
  </rating>
  <reviews>
   928948
  </reviews>
  <new>
   -
  </new>
 </clothing>
 <clothing>
  <id>
   916342836
  </id>
  <name>
   Lacoste Blouse D-4819
  </name>
  <category>
   Blouse
  </category>
  <size>
   M
  </size>
  <color>
   Красный
  </color>
  <material>
   Шелк
  </material>
  <price>
   537366
  </price>
  <rating>
   4.88
  </rating>
  <reviews>
   190948
  </reviews>
  <new>
   +
  </new>
  <sporty>
   yes
  </sporty>
 </clothing>
 <clothing>
  <id>
   513419584
  </id>
  <name>
   Vans Blouse J-4809
  </name>
  <category>
   Blouse
  </category>
  <size>
   XL
  </size>
  <color>
   Голубой
  </color>
  <material>
   Хлопок
  </material>
  <price>
   629099
  </price>
  <rating>
   4.23
  </rating>
  <reviews>
   432748
  </reviews>
  <sporty>
   no
  </sporty>
 </clothing>
 <clothing>
  <id>
   173202397
  </id>
  <name>
   Vans Blouse P-8674
  </name>
  <category>
   Blouse
  </category>
  <size>
   L
  </size>
  <color>
   Зеленый
  </color>
  <material>
   Шелк
  </material>
  <price>
   343786
  </price>
  <rating>
   3.94
  </rating>
  <reviews>
   324484
  </reviews>
  <exclusive>
   no
  </exclusive>
  <sporty>
   yes
  </sporty>
 </clothing>
 <clothing>
  <id>
   784743554
  </id>
  <name>
   Adidas Jacket L-8113
  </name>
  <category>
   Jacket
  </category>
  <size>
   M
  </size>
  <color>
   Зеленый
  </color>
  <material>
   Кожа
  </material>
  <price>
   282393
  </price>
  <rating>
   4.46
  </rating>
  <reviews>
   298926
  </reviews>
  <sporty>
   yes
  </sporty>
 </clothing>
 <clothing>
  <id>
   521155059
  </id>
  <name>
   Asics Belts A-7809
  </name>
  <category>
   Belts
  </category>
  <size>
   L
  </size>
  <color>
   Голубой
  </color>
  <material>
   Шерсть
  </material>
  <price>
   884781
  </price>
  <rating>
   1.64
  </rating>
  <reviews>
   10087
  </reviews>
  <new>
   -
  </new>
  <exclusive>
   yes
  </exclusive>
 </clothing>
 <clothing>
  <id>
   905223413
  </id>
  <name>
   Addidas Handbags G-4538
  </name>
  <category>
   Handbags
  </category>
  <size>
   L
  </size>
  <color>
   Синий
  </color>
  <material>
   Хлопок
  </material>
  <price>
   809137
  </price>
  <rating>
   4.18
  </rating>
  <reviews>
   362897
  </reviews>
  <exclusive>
   no
  </exclusive>
 </clothing>
 <clothing>
  <id>
   410547591
  </id>
  <name>
   Ellesse Hat L-2294
  </name>
  <category>
   Hat
  </category>
  <size>
   XL
  </size>
  <color>
   Оранжевый
  </color>
  <material>
   Нейлон
  </material>
  <price>
   730904
  </price>
  <rating>
   4.09
  </rating>
  <reviews>
   433922
  </reviews>
  <exclusive>
   yes
  </exclusive>
  <sporty>
   no
  </sporty>
 </clothing>
 <clothing>
  <id>
   362306520
  </id>
  <name>
   Converse Skirt E-5009
  </name>
  <category>
   Skirt
  </category>
  <size>
   L
  </size>
  <color>
   Оранжевый
  </color>
  <material>
   Шелк
  </material>
  <price>
   718251
  </price>
  <rating>
   3.08
  </rating>
  <reviews>
   885601
  </reviews>
  <new>
   +
  </new>
 </clothing>
 <clothing>
  <id>
   311677288
  </id>
  <name>
   Vans Hat B-6065
  </name>
  <category>
   Hat
  </category>
  <size>
   M
  </size>
  <color>
   Оранжевый
  </color>
  <material>
   Кожа
  </material>
  <price>
   512429
  </price>
  <rating>
   2.77
  </rating>
  <reviews>
   190442
  </reviews>
  <exclusive>
   no
  </exclusive>
  <sporty>
   no
  </sporty>
 </clothing>
 <clothing>
  <id>
   462187587
  </id>
  <name>
   Puma Umbrellas N-5082
  </name>
  <category>
   Umbrellas
  </category>
  <size>
   XXL
  </size>
  <color>
   Голубой
  </color>
  <material>
   Вискоза
  </material>
  <price>
   286019
  </price>
  <rating>
   1.79
  </rating>
  <reviews>
   566791
  </reviews>
  <new>
   -
  </new>
  <exclusive>
   yes
  </exclusive>
  <sporty>
   no
  </sporty>
 </clothing>
 <clothing>
  <id>
   952901551
  </id>
  <name>
   Vans Blouse V-5177
  </name>
  <category>
   Blouse
  </category>
  <size>
   XXL
  </size>
  <color>
   Желтый
  </color>
  <material>
   Лен
  </material>
  <price>
   829023
  </price>
  <rating>
   4.36
  </rating>
  <reviews>
   25086
  </reviews>
  <new>
   +
  </new>
  <exclusive>
   no
  </exclusive>
  <sporty>
   no
  </sporty>
 </clothing>
 <clothing>
  <id>
   337701580
  </id>
  <name>
   Puma Jacket Z-7629
  </name>
  <category>
   Jacket
  </category>
  <size>
   M
  </size>
  <color>
   Зеленый
  </color>
  <material>
   Кожа
  </material>
  <price>
   418664
  </price>
  <rating>
   3.09
  </rating>
  <reviews>
   943964
  </reviews>
  <new>
   +
  </new>
  <sporty>
   yes
  </sporty>
 </clothing>
 <clothing>
  <id>
   668630002
  </id>
  <name>
   Brooks Pants X-9427
  </name>
  <category>
   Pants
  </category>
  <size>
   XL
  </size>
  <color>
   Желтый
  </color>
  <material>
   Лен
  </material>
  <price>
   315215
  </price>
  <rating>
   3.46
  </rating>
  <reviews>
   679753
  </reviews>
 </clothing>
 <clothing>
  <id>
   761159676
  </id>
  <name>
   Vans Belts Q-7686
  </name>
  <category>
   Belts
  </category>
  <size>
   M
  </size>
  <color>
   Синий
  </color>
  <material>
   Шелк
  </material>
  <price>
   900905
  </price>
  <rating>
   4.18
  </rating>
  <reviews>
   35540
  </reviews>
  <new>
   +
  </new>
  <exclusive>
   yes
  </exclusive>
 </clothing>
 <clothing>
  <id>
   612228080
  </id>
  <name>
   Fila Socks W-9415
  </name>
  <category>
   Socks
  </category>
  <size>
   M
  </size>
  <color>
   Красный
  </color>
  <material>
   Кожа
  </material>
  <price>
   832063
  </price>
  <rating>
   3.9
  </rating>
  <reviews>
   342369
  </reviews>
  <new>
   +
  </new>
 </clothing>
 <clothing>
  <id>
   612191802
  </id>
  <name>
   New Balance Pants A-2456
  </name>
  <category>
   Pants
  </category>
  <size>
   M
  </size>
  <color>
   Зеленый
  </color>
  <material>
   Нейлон
  </material>
  <price>
   548854
  </price>
  <rating>
   4.81
  </rating>
  <reviews>
   681332
  </reviews>
  <new>
   -
  </new>
  <exclusive>
   no
  </exclusive>
  <sporty>
   no
  </sporty>
 </clothing>
 <clothing>
  <id>
   817151748
  </id>
  <name>
   Adidas Dress A-1756
  </name>
  <category>
   Dress
  </category>
  <size>
   S
  </size>
  <color>
   Желтый
  </color>
  <material>
   Полиэстер
  </material>
  <price>
   388787
  </price>
  <rating>
   3.07
  </rating>
  <reviews>
   866848
  </reviews>
  <new>
   +
  </new>
 </clothing>
 <clothing>
  <id>
   488475902
  </id>
  <name>
   Addidas Belts P-5181
  </name>
  <category>
   Belts
  </category>
  <size>
   L
  </size>
  <color>
   Зеленый
  </color>
  <material>
   Нейлон
  </material>
  <price>
   733794
  </price>
  <rating>
   3.39
  </rating>
  <reviews>
   152911
  </reviews>
  <new>
   -
  </new>
  <exclusive>
   yes
  </exclusive>
 </clothing>
 <clothing>
  <id>
   497953526
  </id>
  <name>
   Reebok Belts O-7467
  </name>
  <category>
   Belts
  </category>
  <size>
   S
  </size>
  <color>
   Желтый
  </color>
  <material>
   Хлопок
  </material>
  <price>
   617251
  </price>
  <rating>
   2.09
  </rating>
  <reviews>
   784132
  </reviews>
  <exclusive>
   no
  </exclusive>
 </clothing>
 <clothing>
  <id>
   795212794
  </id>
  <name>
   Reebok Handbags I-5356
  </name>
  <category>
   Handbags
  </category>
  <size>
   M
  </size>
  <color>
   Оранжевый
  </color>
  <material>
   Вискоза
  </material>
  <price>
   559125
  </price>
  <rating>
   3.32
  </rating>
  <reviews>
   551003
  </reviews>
  <new>
   -
  </new>
  <exclusive>
   no
  </exclusive>
  <sporty>
   yes
  </sporty>
 </clothing>
 <clothing>
  <id>
   827907616
  </id>
  <name>
   Nike Blouse G-3625
  </name>
  <category>
   Blouse
  </category>
  <size>
   XL
  </size>
  <color>
   Синий
  </color>
  <material>
   Полиэстер
  </material>
  <price>
   219154
  </price>
  <rating>
   3.96
  </rating>
  <reviews>
   338274
  </reviews>
 </clothing>
 <clothing>
  <id>
   642805980
  </id>
  <name>
   New Balance Pants K-6847
  </name>
  <category>
   Pants
  </category>
  <size>
   S
  </size>
  <color>
   Голубой
  </color>
  <material>
   Шелк
  </material>
  <price>
   222170
  </price>
  <rating>
   2.9
  </rating>
  <reviews>
   916756
  </reviews>
  <exclusive>
   yes
  </exclusive>
 </clothing>
</clothing-items>
